python_sqs_consumer/__init__.py
python_sqs_consumer/__main__.py
python_sqs_consumer/cli.py
python_sqs_consumer/processor.py
python_sqs_consumer/sqs_consumer_pool.py
python_sqs_consumer-0.0.5.dist-info/LICENSE
python_sqs_consumer-0.0.5.dist-info/WHEEL
python_sqs_consumer-0.0.5.dist-info/METADATA
python_sqs_consumer-0.0.5.dist-info/RECORD
